contextguard/__init__.py
contextguard/adapters/__init__.py
contextguard/adapters/budgeted_provider.py
contextguard/adapters/chroma.py
contextguard/adapters/circuit_breaker_provider.py
contextguard/adapters/circuit_breaker_retriever.py
contextguard/adapters/langchain.py
contextguard/adapters/llamaindex.py
contextguard/adapters/openai_provider.py
contextguard/adapters/qdrant.py
contextguard/adapters/retrying_provider.py
contextguard/adapters/retrying_retriever.py
contextguard/core/__init__.py
contextguard/core/instrumentation.py
contextguard/core/merge.py
contextguard/core/settings.py
contextguard/core/specs.py
contextguard/core/trace.py
contextguard/eval/__init__.py
contextguard/eval/harness.py
contextguard/eval/metrics.py
contextguard/eval/datasets/__init__.py
contextguard/eval/datasets/climate_fever.py
contextguard/eval/datasets/fever.py
contextguard/eval/datasets/mtrag_coral.py
contextguard/eval/datasets/scifact.py
contextguard/generate/__init__.py
contextguard/generate/generator.py
contextguard/pipeline/__init__.py
contextguard/pipeline/async_runner.py
contextguard/retrieve/__init__.py
contextguard/retrieve/gating.py
contextguard/retrieve/planner.py
contextguard/retrieve/protocols.py
contextguard/retrieve/rerank.py
contextguard/stores/__init__.py
contextguard/stores/cloud.py
contextguard/stores/postgres.py
contextguard/stores/protocols.py
contextguard/stores/sqlite.py
contextguard/verify/__init__.py
contextguard/verify/aggregate.py
contextguard/verify/claim_splitter.py
contextguard/verify/judges.py
contextguard/verify/nli.py
contextguard/verify/numeric.py
contextguard/verify/rationale.py
contextguard/verify/report.py
llm_contextguard-0.1.0.dist-info/METADATA
llm_contextguard-0.1.0.dist-info/WHEEL
llm_contextguard-0.1.0.dist-info/licenses/LICENSE
llm_contextguard-0.1.0.dist-info/RECORD
