Metadata-Version: 2.4
Name: llm-contextguard
Version: 0.1.0
Summary: State-contracted verification and explainable retrieval gating for agentic RAG.
Project-URL: Homepage, https://github.com/ahmedjawedaj/contextguard
Project-URL: Repository, https://github.com/ahmedjawedaj/contextguard
Project-URL: Issues, https://github.com/ahmedjawedaj/contextguard/issues
Project-URL: Documentation, https://ahmedjawedaj.github.io/contextguard/
Author: ContextGuard Contributors
License: MIT License
License-File: LICENSE
Keywords: llm,provenance,rag,retrieval,traceability,verification
Classifier: Development Status :: 3 - Alpha
Classifier: Intended Audience :: Developers
Classifier: License :: OSI Approved :: MIT License
Classifier: Programming Language :: Python
Classifier: Programming Language :: Python :: 3
Classifier: Programming Language :: Python :: 3 :: Only
Classifier: Programming Language :: Python :: 3.9
Classifier: Programming Language :: Python :: 3.10
Classifier: Programming Language :: Python :: 3.11
Classifier: Programming Language :: Python :: 3.12
Classifier: Topic :: Scientific/Engineering :: Artificial Intelligence
Classifier: Topic :: Software Development :: Libraries
Classifier: Typing :: Typed
Requires-Python: >=3.9
Requires-Dist: pydantic>=2.6
Provides-Extra: chroma
Requires-Dist: chromadb>=0.5.0; extra == 'chroma'
Provides-Extra: cloud
Requires-Dist: boto3>=1.26.0; extra == 'cloud'
Provides-Extra: demo
Requires-Dist: graphviz; extra == 'demo'
Provides-Extra: dev
Requires-Dist: mypy>=1.8; extra == 'dev'
Requires-Dist: pytest>=7.0; extra == 'dev'
Requires-Dist: ruff>=0.5; extra == 'dev'
Provides-Extra: docs
Requires-Dist: mkdocs-material>=9.5.0; extra == 'docs'
Requires-Dist: mkdocs>=1.6.0; extra == 'docs'
Requires-Dist: mkdocstrings[python]>=0.25.0; extra == 'docs'
Provides-Extra: lint
Requires-Dist: ruff>=0.5; extra == 'lint'
Provides-Extra: llm
Requires-Dist: openai>=1.0.0; extra == 'llm'
Provides-Extra: nli
Requires-Dist: sentence-transformers; extra == 'nli'
Provides-Extra: qdrant
Requires-Dist: qdrant-client>=1.7.0; extra == 'qdrant'
Provides-Extra: typecheck
Requires-Dist: mypy>=1.8; extra == 'typecheck'
